AUTHORS.rst
HISTORY.rst
LICENSE
MANIFEST.in
README.rst
requirements.txt
setup.cfg
setup.py
docs/Makefile
docs/source/authors.rst
docs/source/conf.py
docs/source/history.rst
docs/source/index.rst
docs/source/installation.rst
docs/source/intro.rst
docs/source/package.rst
docs/source/quickstart.rst
docs/source/readme.rst
docs/source/usage.rst
pebaystats/__init__.py
pebaystats/dstats.py
pebaystats.egg-info/PKG-INFO
pebaystats.egg-info/SOURCES.txt
pebaystats.egg-info/dependency_links.txt
pebaystats.egg-info/not-zip-safe
pebaystats.egg-info/requires.txt
pebaystats.egg-info/top_level.txt