Metadata-Version: 1.1
Name: pebaystats
Version: 0.4
Summary: descriptive statistics using Pebay results
Home-page: http://github.com/brillozon-code/pebaystats
Author: Mike Martinez
Author-email: brillozon@gmail.com
License: Apache License 2.0
Download-URL: https://github.com/brillozon-code/pebaystats/archive/0.1.tar.gz
Platform: UNKNOWN
Classifier: Intended Audience :: Science/Research
Classifier: Programming Language :: Python :: 2.7
Classifier: Topic :: Scientific/Engineering :: Mathematics
